priorityx/__init__.py
priorityx/api.py
priorityx/metrics.py
priorityx/core/__init__.py
priorityx/core/filters.py
priorityx/core/glmm.py
priorityx/core/quadrants.py
priorityx/tracking/__init__.py
priorityx/tracking/drivers.py
priorityx/tracking/movement.py
priorityx/tracking/transitions.py
priorityx/utils/__init__.py
priorityx/utils/helpers.py
priorityx/viz/__init__.py
priorityx/viz/matrix.py
priorityx/viz/timeline.py
priorityx/viz/trajectory.py
priorityx-0.4.0.dist-info/METADATA
priorityx-0.4.0.dist-info/WHEEL
priorityx-0.4.0.dist-info/licenses/LICENSE
priorityx-0.4.0.dist-info/RECORD
