Metadata-Version: 2.4
Name: priorityx
Version: 0.4.0
Summary: Entity prioritization and escalation detection using GLMM statistical models
Project-URL: Homepage, https://github.com/okkymabruri/priorityx
Project-URL: Repository, https://github.com/okkymabruri/priorityx
Project-URL: Issues, https://github.com/okkymabruri/priorityx/issues
Author-email: Okky Mabruri <okkymbrur@gmail.com>
License: MIT
License-File: LICENSE
Keywords: escalation-detection,glmm,prioritization,risk-analysis,statistical-modeling
Classifier: Development Status :: 5 - Production/Stable
Classifier: Intended Audience :: Developers
Classifier: Intended Audience :: Science/Research
Classifier: License :: OSI Approved :: MIT License
Classifier: Programming Language :: Python :: 3
Classifier: Programming Language :: Python :: 3.10
Classifier: Programming Language :: Python :: 3.11
Classifier: Programming Language :: Python :: 3.12
Classifier: Topic :: Scientific/Engineering
Classifier: Topic :: Software Development :: Libraries :: Python Modules
Requires-Python: >=3.10
Requires-Dist: adjusttext>=1.3.0
Requires-Dist: matplotlib>=3.9.4
Requires-Dist: pandas>=2.3.3
Requires-Dist: statsmodels>=0.14.5
